{
  "$schema": "http://json-schema.org/draft-07/schema#",
  "$id": "https://prebid.org/schemas/pbs/adot.json",
  "title": "The Adot bidder params (Prebid Server)",
  "description": "A schema which validates params accepted by Adot adapter",
  "x-source-url": "https://github.com/prebid/prebid-server/blob/99009c08fb6204ec10f236653a7fc47c229339c3/static/bidder-params/adot.json",
  "type": "object",
  "properties": {
    "placementId": {
      "type": "string",
      "description": "An ID which identifies this placement of the impression"
    },
    "parallax": {
      "type": "boolean",
      "description": "It determines if the wanted advertising format is a parallax."
    },
    "publisherPath": {
      "type": "string",
      "enum": [
        "/hubvisor",
        "/spotx"
      ],
      "description": "An optional path used in the bid endpoint. Only '/hubvisor' and '/spotx' are allowed."
    }
  },
  "required": []
}
