{
  "$schema": "http://json-schema.org/draft-07/schema#",
  "$id": "https://prebid.org/schemas/pbs/sa_lunamedia.json",
  "title": "Sa_Lunamedia bidder params (Prebid Server)",
  "description": "A schema which validates params accepted by the Sa_Lunamedia adapter",
  "x-source-url": "https://github.com/prebid/prebid-server/blob/99009c08fb6204ec10f236653a7fc47c229339c3/static/bidder-params/sa_lunamedia.json",
  "type": "object",
  "properties": {
    "key": {
      "type": "string",
      "description": "network or placement key"
    },
    "type": {
      "type": "string",
      "enum": [
        "network",
        "publisher"
      ]
    }
  },
  "required": [
    "key",
    "type"
  ]
}
