{
  "$schema": "http://json-schema.org/draft-07/schema#",
  "$id": "https://prebid.org/schemas/pbjs/digitalMatter.json",
  "title": "Digital Matter bidder params (Prebid.js)",
  "description": "Generated from prebid.github.io dev-docs/bidders (digitalmatter.md).",
  "x-source-url": "https://github.com/prebid/prebid.github.io/blob/e2559b3ae8367f0a851736c18ee18965806e803a/dev-docs/bidders/digitalmatter.md",
  "type": "object",
  "properties": {
    "accountId": {
      "type": "string",
      "description": "Account ID, provided by Digital Matter"
    },
    "siteId": {
      "type": "string",
      "description": "Site ID, provided by Digital Matter"
    }
  },
  "additionalProperties": false,
  "allOf": [
    {
      "required": [
        "accountId"
      ]
    },
    {
      "required": [
        "siteId"
      ]
    }
  ]
}
